gallery/trivial.png
opentea/.DS_Store
opentea/__init__.py
opentea/cli.py
opentea/maraudersmap.log
opentea/process_utils.py
opentea/__pycache__/__init__.cpython-311.pyc
opentea/__pycache__/__init__.cpython-314.pyc
opentea/__pycache__/__init__.cpython-39.pyc
opentea/__pycache__/cli.cpython-311.pyc
opentea/__pycache__/cli.cpython-39.pyc
opentea/__pycache__/process_utils.cpython-311.pyc
opentea/__pycache__/process_utils.cpython-314.pyc
opentea/__pycache__/process_utils.cpython-39.pyc
opentea/examples/dataset_to_gui.yml
opentea/examples/calculator/.DS_Store
opentea/examples/calculator/__init__.py
opentea/examples/calculator/callback_tab1.py
opentea/examples/calculator/dataset_from_gui.yml
opentea/examples/calculator/schema_calculator.yaml
opentea/examples/calculator/startup.py
opentea/examples/calculator/__pycache__/__init__.cpython-311.pyc
opentea/examples/calculator/__pycache__/__init__.cpython-39.pyc
opentea/examples/calculator/__pycache__/startup.cpython-311.pyc
opentea/examples/calculator/__pycache__/startup.cpython-39.pyc
opentea/examples/simple/.tmp_docu.html
opentea/examples/simple/__init__.py
opentea/examples/simple/process_controleifreq.py
opentea/examples/simple/schema_simple.yaml
opentea/examples/simple/startup.py
opentea/examples/simple/test-pattern-tv.jpg
opentea/examples/simple/test.png
opentea/examples/simple/test.py
opentea/examples/simple/vegetable-icon-png-16.png
opentea/examples/simple/__pycache__/__init__.cpython-311.pyc
opentea/examples/simple/__pycache__/__init__.cpython-39.pyc
opentea/examples/simple/__pycache__/startup.cpython-311.pyc
opentea/examples/simple/__pycache__/startup.cpython-39.pyc
opentea/examples/trivial/__init__.py
opentea/examples/trivial/custom_callback.py
opentea/examples/trivial/dataset_from_gui.yml
opentea/examples/trivial/dataset_to_gui.yml
opentea/examples/trivial/schema_trivial.yaml
opentea/examples/trivial/startup.py
opentea/examples/trivial/__pycache__/__init__.cpython-311.pyc
opentea-3.11.0.dist-info/licenses/LICENSE
opentea-3.11.0.dist-info/METADATA
opentea-3.11.0.dist-info/WHEEL
opentea-3.11.0.dist-info/entry_points.txt
opentea-3.11.0.dist-info/top_level.txt
opentea-3.11.0.dist-info/RECORD
