Metadata-Version: 2.4
Name: opentea
Version: 3.11.0
Summary: Graphical User Interface engine based upon Schema
Author: Antoine Dauptain, Aimad Er-raiy, L. F. Pereira
Author-email: coop@cerfacs.fr
License: CeCILL-B License
Project-URL: Homepage, https://gitlab.com/cerfacs/opentea3
Project-URL: Documentation, https://opentea.readthedocs.io/en/latest/
Project-URL: Issues, https://gitlab.com/cerfacs/opentea3/-/issues
Keywords: GUI,SCHEMA,Tkinter
Classifier: Programming Language :: Python :: 3.7
Classifier: Programming Language :: Python :: 3.8
Classifier: Programming Language :: Python :: 3.9
Classifier: Programming Language :: Python :: 3.10
Classifier: Programming Language :: Python :: 3.11
Classifier: Programming Language :: Python :: 3.12
Classifier: Programming Language :: Python :: 3.13
Requires-Python: >=3.7
License-File: LICENSE
Requires-Dist: arnica>=1.14.2
Requires-Dist: numpy>=1.16.2
Requires-Dist: h5py>=2.6.0
Requires-Dist: loguru
Requires-Dist: colorama
Requires-Dist: markdown
Requires-Dist: Pillow>=5.4.1
Requires-Dist: jsonschema
Requires-Dist: PyYAML>=3.13
Requires-Dist: nob>=0.4.1
Requires-Dist: nobvisual>=1.0.0
Requires-Dist: requests
Requires-Dist: click
Requires-Dist: tiny_3d_engine>=0.3.4
Requires-Dist: matplotlib
Requires-Dist: importlib-resources>=5.0; python_version < "3.9"
Provides-Extra: docs
Requires-Dist: myst-parser; extra == "docs"
Requires-Dist: sphinx_rtd_theme; extra == "docs"
Provides-Extra: apps
Requires-Dist: neverd; extra == "apps"
Dynamic: license-file
